xlitellm/__init__.py
xlitellm/client.py
xlitellm-0.2.4.dist-info/METADATA
xlitellm-0.2.4.dist-info/WHEEL
xlitellm-0.2.4.dist-info/top_level.txt
xlitellm-0.2.4.dist-info/RECORD
