Metadata-Version: 2.2
Name: xlitellm
Version: 0.2.4
Summary: A client library for making requests to various LLMs through a unified interface
Author: Sam Meng
Classifier: Programming Language :: Python :: 3
Classifier: Operating System :: OS Independent
Requires-Python: >=3.11
Requires-Dist: litellm==1.58.1
Requires-Dist: boto3==1.35.54
Dynamic: author
Dynamic: classifier
Dynamic: description
Dynamic: description-content-type
Dynamic: requires-dist
Dynamic: requires-python
Dynamic: summary
